LICENSE
setup.py
tsc_draw/__init__.py
tsc_draw/draw.py
tsc_draw.egg-info/PKG-INFO
tsc_draw.egg-info/SOURCES.txt
tsc_draw.egg-info/dependency_links.txt
tsc_draw.egg-info/requires.txt
tsc_draw.egg-info/top_level.txt