Metadata-Version: 2.1
Name: tsc-draw
Version: 0.8
Summary: 绘图
Home-page: https://github.com/aitsc/tsc-draw
Author: tanshicheng
License: GPLv3
Keywords: tools
Platform: UNKNOWN
Classifier: Intended Audience :: Developers
Classifier: License :: OSI Approved :: GNU General Public License v3 (GPLv3)
Classifier: Programming Language :: Python :: 3 :: Only
Classifier: Topic :: Software Development :: Libraries
Requires-Python: >=3.6
License-File: LICENSE
